odoo/addons/account_move_propagate_ref/README.rst
odoo/addons/account_move_propagate_ref/__init__.py
odoo/addons/account_move_propagate_ref/__manifest__.py
odoo/addons/account_move_propagate_ref/i18n/account_move_propagate_ref.pot
odoo/addons/account_move_propagate_ref/i18n/ca.po
odoo/addons/account_move_propagate_ref/models/__init__.py
odoo/addons/account_move_propagate_ref/models/account_move.py
odoo/addons/account_move_propagate_ref/readme/CONTRIBUTORS.rst
odoo/addons/account_move_propagate_ref/readme/DESCRIPTION.rst
odoo/addons/account_move_propagate_ref/static/description/icon.png
odoo/addons/account_move_propagate_ref/static/description/index.html
odoo/addons/account_move_propagate_ref/tests/__init__.py
odoo/addons/account_move_propagate_ref/tests/test_propagate_ref.py
odoo/addons/account_move_propagate_ref/wizard/__init__.py
odoo/addons/account_move_propagate_ref/wizard/account_move_reversal.py
odoo14_addon_account_move_propagate_ref-14.0.1.0.1.dist-info/METADATA
odoo14_addon_account_move_propagate_ref-14.0.1.0.1.dist-info/WHEEL
odoo14_addon_account_move_propagate_ref-14.0.1.0.1.dist-info/top_level.txt
odoo14_addon_account_move_propagate_ref-14.0.1.0.1.dist-info/RECORD
