Metadata-Version: 2.1
Name: odoo14-addon-account-move-propagate-ref
Version: 14.0.1.0.1
Summary: Propagate ref when reversing and recreating an accounting move
Home-page: https://github.com/OCA/account-invoicing
Author: Camptocamp, Odoo Community Association (OCA)
Author-email: support@odoo-community.org
License: AGPL-3
Platform: UNKNOWN
Classifier: Programming Language :: Python
Classifier: Framework :: Odoo
Classifier: Framework :: Odoo :: 14.0
Classifier: License :: OSI Approved :: GNU Affero General Public License v3
Requires-Python: >=3.6
Requires-Dist: odoo (<14.1dev,>=14.0a)
